pygqlc/GraphQLClient.py
pygqlc/__init__.py
pygqlc/__main__.py
pygqlc/version.py
src/GraphQLClient.py
src/__init__.py
src/__main__.py
src/version.py
pygqlc_valiot-0.1.1.dist-info/LICENCE
pygqlc_valiot-0.1.1.dist-info/METADATA
pygqlc_valiot-0.1.1.dist-info/WHEEL
pygqlc_valiot-0.1.1.dist-info/entry_points.txt
pygqlc_valiot-0.1.1.dist-info/top_level.txt
pygqlc_valiot-0.1.1.dist-info/RECORD
